pyseat/HierachicalEmbedding.py
pyseat/SEAT.py
pyseat/__init__.py
pyseat/graph_metric.py
pyseat/version.py
pyseat-0.0.1.4.dist-info/METADATA
pyseat-0.0.1.4.dist-info/WHEEL
pyseat-0.0.1.4.dist-info/top_level.txt
pyseat-0.0.1.4.dist-info/RECORD
