Metadata-Version: 2.1
Name: pyseat
Version: 0.0.1.4
Summary: Structure Entropy hierArchy deTection (SEAT) for clustering, ordering, and embedding
Home-page: https://github.com/deepomicslab/seat
Author: Lingxi Chen
Author-email: chanlingxi@gmail.com
License: UNKNOWN
Platform: UNKNOWN
Classifier: Programming Language :: Python :: 3
Classifier: Operating System :: OS Independent
Requires-Dist: cycler (>=0.11.0)
Requires-Dist: fonttools (>=4.37.1)
Requires-Dist: joblib (>=1.1.0)
Requires-Dist: kiwisolver (>=1.4.4)
Requires-Dist: kmeans1d (>=0.3.1)
Requires-Dist: matplotlib (>=3.5.3)
Requires-Dist: networkx (>=2.8.6)
Requires-Dist: numpy (>=1.23.3)
Requires-Dist: packaging (>=21.3)
Requires-Dist: pandas (>=1.4.4)
Requires-Dist: Pillow (>=9.2.0)
Requires-Dist: pyparsing (>=3.0.9)
Requires-Dist: python-dateutil (>=2.8.2)
Requires-Dist: pytz (>=2022.2.1)
Requires-Dist: scikit-learn (>=1.1.2)
Requires-Dist: scipy (>=1.9.1)
Requires-Dist: seaborn (>=0.12.0)
Requires-Dist: six (>=1.16.0)
Requires-Dist: scikit-learn (>=0.0)
Requires-Dist: threadpoolctl (>=3.1.0)
Requires-Dist: torch (>=1.12.1)
Requires-Dist: typing-extensions (>=4.3.0)
